drill_bits/__init__.py
drill_bits/io/__init__.py
drill_bits/io/io_utils.py
drill_bits/io/str_utils.py
drill_bits/operation/__init__.py
drill_bits/operation/base_operation.py
drill_bits-0.0.5.dist-info/METADATA
drill_bits-0.0.5.dist-info/WHEEL
drill_bits-0.0.5.dist-info/licenses/LICENSE
drill_bits-0.0.5.dist-info/RECORD
