Metadata-Version: 2.1
Name: drill-bits
Version: 0.0.5
Summary: Drill-bits: Handy tools for ML in Python
Project-URL: Homepage, https://pypi.org/project/drill-bits/
Author-email: jiujiuche <jiujiuche@gmail.com>
License-File: LICENSE
Classifier: License :: OSI Approved :: MIT License
Classifier: Operating System :: OS Independent
Classifier: Programming Language :: Python :: 3
Requires-Python: >=3.7
Requires-Dist: numpy
Requires-Dist: pillow
